CHANGELOG.md
LICENSE
README.md
click_trig/__init__.py
click_trig/trig.py
click_trig-0.1.7.dist-info/entry_points.txt
click_trig-0.1.7.dist-info/LICENSE
click_trig-0.1.7.dist-info/WHEEL
click_trig-0.1.7.dist-info/METADATA
click_trig-0.1.7.dist-info/RECORD
